LICENSE
validate_telegram_markdown/__init__.py
validate_telegram_markdown-0.1.0.dist-info/LICENSE
validate_telegram_markdown-0.1.0.dist-info/METADATA
validate_telegram_markdown-0.1.0.dist-info/WHEEL
validate_telegram_markdown-0.1.0.dist-info/RECORD
