Metadata-Version: 2.1
Name: validate-telegram-markdown
Version: 0.1.0
Summary: Validate Telegram flavored markdown
Home-page: https://github.com/skarrok/validate-telegram-markdown
License: MIT
Keywords: telegram,markdown,validate
Author: skarrok
Author-email: skarrork.h@gmail.com
Requires-Python: >=3.10,<4.0
Classifier: Environment :: Console
Classifier: License :: OSI Approved :: MIT License
Classifier: Operating System :: OS Independent
Classifier: Programming Language :: Python :: 3
Classifier: Programming Language :: Python :: 3.10
Classifier: Programming Language :: Python :: 3.11
Classifier: Programming Language :: Python :: 3.12
Classifier: Topic :: Software Development :: Libraries :: Python Modules
Classifier: Topic :: Software Development :: Quality Assurance
Classifier: Topic :: Utilities
Project-URL: Repository, https://github.com/skarrok/validate-telegram-markdown
